tabpfn_client/__init__.py
tabpfn_client/browser_auth.py
tabpfn_client/client.py
tabpfn_client/config.py
tabpfn_client/constants.py
tabpfn_client/estimator.py
tabpfn_client/prompt_agent.py
tabpfn_client/server_config.yaml
tabpfn_client/service_wrapper.py
tabpfn_client/ui.py
tabpfn_client/tabpfn_common_utils/.git
tabpfn_client/tabpfn_common_utils/.gitignore
tabpfn_client/tabpfn_common_utils/.pre-commit-config.yaml
tabpfn_client/tabpfn_common_utils/README.md
tabpfn_client/tabpfn_common_utils/__init__.py
tabpfn_client/tabpfn_common_utils/expense_estimation.py
tabpfn_client/tabpfn_common_utils/load_test.py
tabpfn_client/tabpfn_common_utils/regression_pred_result.py
tabpfn_client/tabpfn_common_utils/requirements.txt
tabpfn_client/tabpfn_common_utils/ruff.toml
tabpfn_client/tabpfn_common_utils/utils.py
tabpfn_client/tabpfn_common_utils/.github/pull_request_template.md
tabpfn_client/tabpfn_common_utils/.github/workflows/pull_requests.yml
tabpfn_client/tabpfn_common_utils/datasets/X_test.csv
tabpfn_client/tabpfn_common_utils/datasets/X_test_small.csv
tabpfn_client/tabpfn_common_utils/datasets/X_train.csv
tabpfn_client/tabpfn_common_utils/datasets/X_train_small.csv
tabpfn_client/tabpfn_common_utils/datasets/y_train.csv
tabpfn_client/tabpfn_common_utils/datasets/y_train_small.csv
tabpfn_client/tabpfn_common_utils/tests/__init__.py
tabpfn_client/tabpfn_common_utils/tests/test_expense_estimation.py
tabpfn_client/tabpfn_common_utils/tests/test_regression_pred_result.py
tabpfn_client/tabpfn_common_utils/tests/test_utils.py
tabpfn_client/tests/__init__.py
tabpfn_client/tests/mock_tabpfn_server.py
tabpfn_client/tests/quick_test.py
tabpfn_client/tests/quick_test_v1.py
tabpfn_client/tests/integration/__init__.py
tabpfn_client/tests/integration/test_server_config.py
tabpfn_client/tests/integration/test_tabpfn_classifier.py
tabpfn_client/tests/unit/__init__.py
tabpfn_client/tests/unit/test_browser_auth.py
tabpfn_client/tests/unit/test_client.py
tabpfn_client-0.2.8.dist-info/METADATA
tabpfn_client-0.2.8.dist-info/WHEEL
tabpfn_client-0.2.8.dist-info/licenses/LICENSE
tabpfn_client-0.2.8.dist-info/RECORD
