Metadata-Version: 2.4
Name: tabpfn-client
Version: 0.2.8
Summary: API access for TabPFN: Foundation model for tabular data
Project-URL: documentation, https://priorlabs.ai/docs
Project-URL: source, https://github.com/priorlabs/tabpfn-client
License: 
License-File: LICENSE
Classifier: Intended Audience :: Developers
Classifier: Intended Audience :: Science/Research
Classifier: License :: OSI Approved :: Apache Software License
Classifier: Operating System :: MacOS
Classifier: Operating System :: POSIX
Classifier: Operating System :: Unix
Classifier: Programming Language :: Python
Classifier: Programming Language :: Python :: 3
Classifier: Programming Language :: Python :: 3.9
Classifier: Programming Language :: Python :: 3.10
Classifier: Programming Language :: Python :: 3.11
Classifier: Programming Language :: Python :: 3.12
Classifier: Programming Language :: Python :: 3.13
Classifier: Topic :: Scientific/Engineering
Classifier: Topic :: Software Development
Requires-Python: >=3.9
Requires-Dist: backoff<=2.2.1,>=2.2.0
Requires-Dist: httpx[http2]<=0.28.1,>=0.25.0
Requires-Dist: omegaconf<=2.3.0,>=2.1.2
Requires-Dist: pandas<=2.3.3,>=2.1.2
Requires-Dist: password-strength<=0.0.3.post2,>=0.0.3.post2
Requires-Dist: rich<=14.0.0,>=13.7.0
Requires-Dist: scikit-learn<=1.6.1,>=1.3.1
Requires-Dist: sseclient-py<=1.8.0,>=1.8.0
Requires-Dist: tqdm<=4.67.1,>=4.63.0
Requires-Dist: typing-extensions<=4.15.0,>=4.12.2
Requires-Dist: xxhash<=3.6.0,>=1.1.0
Provides-Extra: dev
Requires-Dist: pre-commit==4.2.0; extra == 'dev'
Requires-Dist: pytest==8.4.2; extra == 'dev'
Requires-Dist: respx==0.22.0; extra == 'dev'
Requires-Dist: ruff==0.11.9; extra == 'dev'
Requires-Dist: scikit-learn==1.6.1; extra == 'dev'
Requires-Dist: typing-extensions==4.15.0; extra == 'dev'
